fact_worthiness/__init__.py
fact_worthiness/fact_worthy.py
fact_worthiness/keyword_check.py
fact_worthiness/len_check.py
fact_worthiness/ml_check.py
fact_worthiness/ner_check.py
fact_worthiness/models/classification_model.onnx
fact_worthiness/models/label_encoder_34k.pkl
fact_worthiness/models/onnx_model/config.json
fact_worthiness/models/onnx_model/model_fp16.onnx
fact_worthiness/models/onnx_model/special_tokens_map.json
fact_worthiness/models/onnx_model/tokenizer.json
fact_worthiness/models/onnx_model/tokenizer_config.json
fact_worthiness-0.2.0.dist-info/METADATA
fact_worthiness-0.2.0.dist-info/WHEEL
fact_worthiness-0.2.0.dist-info/entry_points.txt
fact_worthiness-0.2.0.dist-info/top_level.txt
fact_worthiness-0.2.0.dist-info/RECORD
